CESAPI/__init__.py
CESAPI/command.py
CESAPI/connection.py
CESAPI/packet.py
CESAPI/refract.py
CESAPI/sniff.py
CESAPI/test.py
CESAPI/test_command.py
CESAPI/test_connection.py
CESAPI/test_packet.py
CESAPI/test_refract.py
CESAPI/video.py
CESAPI-1.1.3.data/data/LICENSE
CESAPI-1.1.3.dist-info/LICENSE.txt
CESAPI-1.1.3.dist-info/METADATA
CESAPI-1.1.3.dist-info/RECORD
CESAPI-1.1.3.dist-info/WHEEL
CESAPI-1.1.3.dist-info/top_level.txt
