Metadata-Version: 2.1
Name: CESAPI
Version: 1.1.3
Summary: Leica AT4xx laser tracker control modules.
Home-page: https://github.com/MuffinSpawn/Leica
Author: Peter G. Lane
Author-email: muffinspawn@gmail.com
License: MIT License
